apyscript/__init__.py
apyscript/callable/__init__.py
apyscript/callable/callable_util.py
apyscript/color/__init__.py
apyscript/color/color_util.py
apyscript/console/__init__.py
apyscript/console/_trace.py
apyscript/console/assertion.py
apyscript/console/loggers.py
apyscript/converter/__init__.py
apyscript/converter/cast.py
apyscript/display/__init__.py
apyscript/display/begin_fill_interface.py
apyscript/display/child_interface.py
apyscript/display/display_object.py
apyscript/display/fill_alpha_interface.py
apyscript/display/fill_color_interface.py
apyscript/display/graphic_base.py
apyscript/display/graphics.py
apyscript/display/graphics_clear_interface.py
apyscript/display/graphics_expression.py
apyscript/display/height_interface.py
apyscript/display/line_alpha_interface.py
apyscript/display/line_color_interface.py
apyscript/display/line_style_interface.py
apyscript/display/line_thickness_interface.py
apyscript/display/parent_interface.py
apyscript/display/rectangle.py
apyscript/display/sprite.py
apyscript/display/stage.py
apyscript/display/width_interface.py
apyscript/display/x_interface.py
apyscript/display/y_interface.py
apyscript/expression/__init__.py
apyscript/expression/expression_file_util.py
apyscript/expression/expression_variables_util.py
apyscript/expression/var_names.py
apyscript/file/__init__.py
apyscript/file/file_util.py
apyscript/html/__init__.py
apyscript/html/exporter.py
apyscript/html/html_const.py
apyscript/html/html_util.py
apyscript/jslib/__init__.py
apyscript/jslib/jquery.min.js
apyscript/jslib/jslib_util.py
apyscript/jslib/svg.min.js
apyscript/jslib/underscore.min.js
apyscript/string/__init__.py
apyscript/string/indent_util.py
apyscript/string/string_util.py
apyscript/type/__init__.py
apyscript/type/array.py
apyscript/type/boolean.py
apyscript/type/copy_interface.py
apyscript/type/int.py
apyscript/type/number.py
apyscript/type/number_value_interface.py
apyscript/type/string.py
apyscript/type/type_name_interface.py
apyscript-0.4.18.dist-info/LICENSE
apyscript-0.4.18.dist-info/METADATA
apyscript-0.4.18.dist-info/WHEEL
apyscript-0.4.18.dist-info/top_level.txt
apyscript-0.4.18.dist-info/RECORD
