Metadata-Version: 2.1
Name: apyscript
Version: 0.4.18
Summary: apyscript is a Python's frontend library to create html and js file, that has a ActionScript 3 (as3)-like interface.
Home-page: https://github.com/simon-ritchie/apyscript
Maintainer: simon-ritchie
Maintainer-email: 
License: MIT
Platform: UNKNOWN
Classifier: Programming Language :: Python :: 3
Classifier: License :: OSI Approved :: MIT License
Requires-Dist: typing-extensions
